xoog_to_mongodb/__init__.py
xoog_to_mongodb/convert_df_to_df_list.py
XoogMongoFunctions-0.0.1.dist-info/METADATA
XoogMongoFunctions-0.0.1.dist-info/WHEEL
XoogMongoFunctions-0.0.1.dist-info/top_level.txt
XoogMongoFunctions-0.0.1.dist-info/RECORD
